[
 {
  "_assign": null,
  "_comments": null,
  "_liked_by": null,
  "_user_tags": ",dsr",
  "default_value": null,
  "doc_type": "Dispensed for Office Use",
  "docstatus": 0,
  "doctype": "Property Setter",
  "doctype_or_field": "DocField",
  "field_name": "naming_series",
  "modified": "2020-01-08 16:47:03.260880",
  "name": "Dispensed for Office Use-naming_series-options",
  "parent": null,
  "parentfield": null,
  "parenttype": null,
  "property": "options",
  "property_type": "Text",
  "value": "DOU-.YYYY.-.#######"
 },
 {
  "_assign": null,
  "_comments": null,
  "_liked_by": null,
  "_user_tags": ",dsr",
  "default_value": null,
  "doc_type": "Expense Record",
  "docstatus": 0,
  "doctype": "Property Setter",
  "doctype_or_field": "DocField",
  "field_name": "naming_series",
  "modified": "2020-01-08 16:51:04.305145",
  "name": "Expense Record-naming_series-options",
  "parent": null,
  "parentfield": null,
  "parenttype": null,
  "property": "options",
  "property_type": "Text",
  "value": "ER-.YYYY.-.#######"
 },
 {
  "_assign": null,
  "_comments": null,
  "_liked_by": null,
  "_user_tags": ",dsr",
  "default_value": null,
  "doc_type": "Fuel Stock Receipts",
  "docstatus": 0,
  "doctype": "Property Setter",
  "doctype_or_field": "DocField",
  "field_name": "naming_series",
  "modified": "2020-01-08 16:50:14.582907",
  "name": "Fuel Stock Receipts-naming_series-options",
  "parent": null,
  "parentfield": null,
  "parenttype": null,
  "property": "options",
  "property_type": "Text",
  "value": "FSR-.YYYY.-.#######"
 },
 {
  "_assign": null,
  "_comments": null,
  "_liked_by": null,
  "_user_tags": ",dsr",
  "default_value": null,
  "doc_type": "Credit Sales",
  "docstatus": 0,
  "doctype": "Property Setter",
  "doctype_or_field": "DocField",
  "field_name": "naming_series",
  "modified": "2020-01-06 15:37:14.779488",
  "name": "Credit Sales-naming_series-options",
  "parent": null,
  "parentfield": null,
  "parenttype": null,
  "property": "options",
  "property_type": "Text",
  "value": "CST-.YYYY.-.#######"
 },
 {
  "_assign": null,
  "_comments": null,
  "_liked_by": null,
  "_user_tags": ",dsr",
  "default_value": null,
  "doc_type": "Cash Deposited",
  "docstatus": 0,
  "doctype": "Property Setter",
  "doctype_or_field": "DocField",
  "field_name": "naming_series",
  "modified": "2020-01-08 16:46:07.263912",
  "name": "Cash Deposited-naming_series-options",
  "parent": null,
  "parentfield": null,
  "parenttype": null,
  "property": "options",
  "property_type": "Text",
  "value": "CD-.YYYY.-.#######"
 },
 {
  "_assign": null,
  "_comments": null,
  "_liked_by": null,
  "_user_tags": ",dsr",
  "default_value": null,
  "doc_type": "Credit Sales",
  "docstatus": 0,
  "doctype": "Property Setter",
  "doctype_or_field": "DocField",
  "field_name": "naming_series",
  "modified": "2020-01-06 15:37:14.829636",
  "name": "Credit Sales-naming_series-default",
  "parent": null,
  "parentfield": null,
  "parenttype": null,
  "property": "default",
  "property_type": "Text",
  "value": "CST-.YYYY.-.#######"
 },
 {
  "_assign": null,
  "_comments": null,
  "_liked_by": null,
  "_user_tags": ",dsr",
  "default_value": null,
  "doc_type": "Cash Deposited",
  "docstatus": 0,
  "doctype": "Property Setter",
  "doctype_or_field": "DocField",
  "field_name": "naming_series",
  "modified": "2020-01-08 16:46:07.313519",
  "name": "Cash Deposited-naming_series-default",
  "parent": null,
  "parentfield": null,
  "parenttype": null,
  "property": "default",
  "property_type": "Text",
  "value": "CD-.YYYY.-.#######"
 },
 {
  "_assign": null,
  "_comments": null,
  "_liked_by": null,
  "_user_tags": ",dsr",
  "default_value": null,
  "doc_type": "Dispensed for Office Use",
  "docstatus": 0,
  "doctype": "Property Setter",
  "doctype_or_field": "DocField",
  "field_name": "naming_series",
  "modified": "2020-01-08 16:47:03.307439",
  "name": "Dispensed for Office Use-naming_series-default",
  "parent": null,
  "parentfield": null,
  "parenttype": null,
  "property": "default",
  "property_type": "Text",
  "value": "DOU-.YYYY.-.#######"
 },
 {
  "_assign": null,
  "_comments": null,
  "_liked_by": null,
  "_user_tags": ",dsr",
  "default_value": null,
  "doc_type": "Fuel Stock Receipts",
  "docstatus": 0,
  "doctype": "Property Setter",
  "doctype_or_field": "DocField",
  "field_name": "naming_series",
  "modified": "2020-01-08 16:50:14.628071",
  "name": "Fuel Stock Receipts-naming_series-default",
  "parent": null,
  "parentfield": null,
  "parenttype": null,
  "property": "default",
  "property_type": "Text",
  "value": "FSR-.YYYY.-.#######"
 },
 {
  "_assign": null,
  "_comments": null,
  "_liked_by": null,
  "_user_tags": ",dsr",
  "default_value": null,
  "doc_type": "Expense Record",
  "docstatus": 0,
  "doctype": "Property Setter",
  "doctype_or_field": "DocField",
  "field_name": "naming_series",
  "modified": "2020-01-08 16:51:04.351923",
  "name": "Expense Record-naming_series-default",
  "parent": null,
  "parentfield": null,
  "parenttype": null,
  "property": "default",
  "property_type": "Text",
  "value": "ER-.YYYY.-.#######"
 }
]